moniotclient/IotMqttClient.py
moniotclient/__init__.py
moniotclient-1.dist-info/LICENSE.txt
moniotclient-1.dist-info/METADATA
moniotclient-1.dist-info/WHEEL
moniotclient-1.dist-info/top_level.txt
moniotclient-1.dist-info/RECORD
